pychomp/Braids.py
pychomp/CondensationGraph.py
pychomp/CubicalHomology.py
pychomp/DirectedAcyclicGraph.py
pychomp/DirectedGraph.py
pychomp/DrawGradedComplex.py
pychomp/FlowGradedComplex.py
pychomp/InducedSubgraph.py
pychomp/Poset.py
pychomp/StronglyConnectedComponents.py
pychomp/TopologicalSort.py
pychomp/TransitiveClosure.py
pychomp/TransitiveReduction.py
pychomp/__init__.py
pychomp/_chomp.cpython-312-x86_64-linux-gnu.so
pychomp/_chomp/chomp.cpp
pychomp/_chomp/include/Chain.h
pychomp/_chomp/include/Complex.h
pychomp/_chomp/include/ConnectionMatrix.h
pychomp/_chomp/include/CubicalComplex.h
pychomp/_chomp/include/CubicalMorseMatching.h
pychomp/_chomp/include/DualComplex.h
pychomp/_chomp/include/GenericMorseMatching.h
pychomp/_chomp/include/GradedComplex.h
pychomp/_chomp/include/Grading.h
pychomp/_chomp/include/Homology.h
pychomp/_chomp/include/Integer.h
pychomp/_chomp/include/Iterator.h
pychomp/_chomp/include/MorseComplex.h
pychomp/_chomp/include/MorseGradedComplex.h
pychomp/_chomp/include/MorseMatching.h
pychomp/_chomp/include/MorseMatching.hpp
pychomp/_chomp/include/OrderComplex.h
pychomp/_chomp/include/Poset.h
pychomp/_chomp/include/SimplicialComplex.h
pychomp/_chomp/include/common.h
pychomp/_chomp/include/hash.hpp
pychomp2-1.1.1.dist-info/METADATA
pychomp2-1.1.1.dist-info/WHEEL
pychomp2-1.1.1.dist-info/RECORD
pychomp2-1.1.1.dist-info/licenses/LICENSE
